odoo/addons/pms_civitfun/README.rst
odoo/addons/pms_civitfun/__init__.py
odoo/addons/pms_civitfun/__manifest__.py
odoo/addons/pms_civitfun/http.py
odoo/addons/pms_civitfun/controllers/__init__.py
odoo/addons/pms_civitfun/controllers/pms_rest.py
odoo/addons/pms_civitfun/data/auth_jwt_validator.xml
odoo/addons/pms_civitfun/datamodels/__init__.py
odoo/addons/pms_civitfun/datamodels/pms_checkin_partner.py
odoo/addons/pms_civitfun/datamodels/pms_payment.py
odoo/addons/pms_civitfun/datamodels/pms_reservation.py
odoo/addons/pms_civitfun/datamodels/pms_user.py
odoo/addons/pms_civitfun/models/__init__.py
odoo/addons/pms_civitfun/models/pms_property.py
odoo/addons/pms_civitfun/models/res_partner_id_category.py
odoo/addons/pms_civitfun/services/__init__.py
odoo/addons/pms_civitfun/services/pms_checkin_partner_service.py
odoo/addons/pms_civitfun/services/pms_login_service.py
odoo/addons/pms_civitfun/services/pms_payment_service.py
odoo/addons/pms_civitfun/services/pms_reservation_service.py
odoo/addons/pms_civitfun/static/description/Standard3_EN_35860.md
odoo/addons/pms_civitfun/static/description/icon.png
odoo/addons/pms_civitfun/views/pms_property_views.xml
odoo/addons/pms_civitfun/views/res_partner_id_category_views.xml
odoo14_addon_pms_civitfun-14.0.1.0.1.dev7.dist-info/METADATA
odoo14_addon_pms_civitfun-14.0.1.0.1.dev7.dist-info/WHEEL
odoo14_addon_pms_civitfun-14.0.1.0.1.dev7.dist-info/top_level.txt
odoo14_addon_pms_civitfun-14.0.1.0.1.dev7.dist-info/RECORD
